README.md
setup.py
mcbe_data/__init__.py
mcbe_data/get.py
mcbe_data.egg-info/PKG-INFO
mcbe_data.egg-info/SOURCES.txt
mcbe_data.egg-info/dependency_links.txt
mcbe_data.egg-info/top_level.txt
mcbe_data/data/block_states.json
mcbe_data/data/item_table.json