Metadata-Version: 1.1
Name: mcbe-data
Version: 0.1
Summary: Podrum's mcbe Data.
Home-page: https://github.com/Podrum/mcbe_data
Author: Podrum
Author-email: UNKNOWN
License: MIT
Keywords: mcbe,data,python3
Platform: UNKNOWN
Classifier: Development Status :: 5 - Production/Stable
Classifier: Intended Audience :: Developers
Classifier: Topic :: Software Development :: Libraries
Classifier: License :: OSI Approved :: MIT License
Classifier: Programming Language :: Python :: 3.5
Classifier: Programming Language :: Python :: 3.6
Classifier: Programming Language :: Python :: 3.7
Classifier: Programming Language :: Python :: 3.8
Classifier: Programming Language :: Python :: 3.9
